waldiez_studio/__init__.py
waldiez_studio/__main__.py
waldiez_studio/_logging.py
waldiez_studio/_version.py
waldiez_studio/cli.py
waldiez_studio/main.py
waldiez_studio/py.typed
waldiez_studio/config/__init__.py
waldiez_studio/config/lib.py
waldiez_studio/config/settings.py
waldiez_studio/engines/__init__.py
waldiez_studio/engines/base.py
waldiez_studio/engines/factory.py
waldiez_studio/engines/kernel.py
waldiez_studio/engines/notebook_engine.py
waldiez_studio/engines/subprocess_engine.py
waldiez_studio/engines/waldiez_engine.py
waldiez_studio/middleware/__init__.py
waldiez_studio/middleware/extra_headers.py
waldiez_studio/models/__init__.py
waldiez_studio/models/flow.py
waldiez_studio/models/workspace.py
waldiez_studio/routes/__init__.py
waldiez_studio/routes/common.py
waldiez_studio/routes/flow.py
waldiez_studio/routes/terminal_ws.py
waldiez_studio/routes/workspace.py
waldiez_studio/routes/ws.py
waldiez_studio/static/frontend/apple-touch-icon.png
waldiez_studio/static/frontend/browserconfig.xml
waldiez_studio/static/frontend/favicon-32x32.png
waldiez_studio/static/frontend/favicon-48x48.png
waldiez_studio/static/frontend/favicon.ico
waldiez_studio/static/frontend/index.html
waldiez_studio/static/frontend/robots.txt
waldiez_studio/static/frontend/site.webmanifest
waldiez_studio/static/frontend/assets/@braintree-BnqQ9vdI.js
waldiez_studio/static/frontend/assets/@chevrotain-Co5Sw0Ld.js
waldiez_studio/static/frontend/assets/@floating-ui-D64ZPFEY.js
waldiez_studio/static/frontend/assets/@iconify-RJK46K7i.js
waldiez_studio/static/frontend/assets/@mermaid-js-C_T3wcyE.js
waldiez_studio/static/frontend/assets/@monaco-editor-CLJAr0Lq.js
waldiez_studio/static/frontend/assets/@radix-ui-n_FrXABx.js
waldiez_studio/static/frontend/assets/@reduxjs-l0sNRNKZ.js
waldiez_studio/static/frontend/assets/@shikijs-Be_MlHpf.js
waldiez_studio/static/frontend/assets/@tanstack-ClP00k1D.js
waldiez_studio/static/frontend/assets/@waldiez-CDngT8lG.css
waldiez_studio-0.7.1.dist-info/METADATA
waldiez_studio-0.7.1.dist-info/WHEEL
waldiez_studio-0.7.1.dist-info/entry_points.txt
waldiez_studio-0.7.1.dist-info/licenses/LICENSE
waldiez_studio-0.7.1.dist-info/licenses/NOTICE.md
waldiez_studio-0.7.1.dist-info/RECORD
